dyndb/__init__.py
dyndb/cli.py
dyndb/exp.py
dyndb/imp.py
dyndb-0.1.1.dist-info/entry_points.txt
dyndb-0.1.1.dist-info/WHEEL
dyndb-0.1.1.dist-info/METADATA
dyndb-0.1.1.dist-info/RECORD
