Metadata-Version: 2.1
Name: dyndb
Version: 0.1.1
Summary: 
Author: Pascal Prins
Author-email: pascal.prins@foobar-it.com
Requires-Python: >=2.7, !=3.0.*, !=3.1.*, !=3.2.*, !=3.3.*, !=3.4.*, !=3.5.*, !=3.6.*
Classifier: Programming Language :: Python :: 2
Classifier: Programming Language :: Python :: 2.7
Classifier: Programming Language :: Python :: 3
Classifier: Programming Language :: Python :: 3.7
Classifier: Programming Language :: Python :: 3.8
Requires-Dist: boto3 (>=1.12.26,<2.0.0)
Requires-Dist: click (>=7.1.1,<8.0.0)
